{"progress":{"state":"COMPLETED","status":"","start":{"seconds":"1541823431","nanos":778482000},"end":{"seconds":"1541823436","nanos":295856000}},"steps":[],"exposed_outputs":{"steps.0.produce":{"value":"csv_uri","error":null,"raw":null,"dataset_uri":"","csv_uri":"file:///output/predictions/d0ae4bcf-dfb6-4f06-b4fd-d1507815b1a2/d0ae4bcf-dfb6-4f06-b4fd-d1507815b1a2.steps.0.produce.csv","pickle_uri":"","pickle_blob":{"type":"Buffer","data":[]},"plasma_id":{"type":"Buffer","data":[]}}},"fitted_solution_id":"d0ae4bcf-dfb6-4f06-b4fd-d1507815b1a2"}