{"progress":{"state":"COMPLETED","status":"","start":{"seconds":"1542660851","nanos":425453000},"end":{"seconds":"1542660854","nanos":695522000}},"steps":[],"exposed_outputs":{"steps.0.produce":{"value":"csv_uri","error":null,"raw":null,"dataset_uri":"","csv_uri":"file:///output/predictions/db74552b-2ff1-4ee4-97b7-6d720abae4ac/db74552b-2ff1-4ee4-97b7-6d720abae4ac.steps.0.produce.csv","pickle_uri":"","pickle_blob":{"type":"Buffer","data":[]},"plasma_id":{"type":"Buffer","data":[]}}},"fitted_solution_id":"db74552b-2ff1-4ee4-97b7-6d720abae4ac"}