{"progress":{"state":"COMPLETED","status":"Job completed","start":{"seconds":"1541529838","nanos":206797000},"end":{"seconds":"1541529838","nanos":206806000}},"steps":[],"exposed_outputs":{"steps.5.produce":{"value":"csv_uri","error":null,"raw":null,"dataset_uri":"","csv_uri":"file:///output/temp/predictions/0bcf5ebd-df77-480c-9863-eb2ebc22ace5/7cc4f7f5-1d0f-4b98-8fe8-b3b84c9de1d7/steps.5.produce.csv","pickle_uri":"","pickle_blob":{"type":"Buffer","data":[]},"plasma_id":{"type":"Buffer","data":[]}}}}